aws_lambda/__init__.py
aws_lambda/aws_lambda.py
aws_lambda/helpers.py
aws_lambda/project_templates/config.yaml
aws_lambda/project_templates/event.json
aws_lambda/project_templates/service.py
dmn_python_lambda-3.3.1.data/scripts/lambda
dmn_python_lambda-3.3.1.dist-info/METADATA
dmn_python_lambda-3.3.1.dist-info/RECORD
dmn_python_lambda-3.3.1.dist-info/WHEEL
dmn_python_lambda-3.3.1.dist-info/top_level.txt
tests/__init__.py
tests/dev_requirements.txt
tests/functional/__init__.py
tests/unit/__init__.py
