Metadata-Version: 2.1
Name: dmn-python-lambda
Version: 3.3.1
Summary: The bare minimum for a Python app running on Amazon Lambda.
Home-page: https://github.com/nficano/python-lambda
Author: Nick Ficano
Author-email: nficano@gmail.com
License: ISCL
Keywords: python-lambda
Platform: UNKNOWN
Classifier: Development Status :: 2 - Pre-Alpha
Classifier: Intended Audience :: Developers
Classifier: License :: OSI Approved :: ISC License (ISCL)
Classifier: Natural Language :: English
Classifier: Programming Language :: Python :: 2
Classifier: Programming Language :: Python :: 2.6
Classifier: Programming Language :: Python :: 2.7
Classifier: Programming Language :: Python :: 3
Classifier: Programming Language :: Python :: 3.3
Classifier: Programming Language :: Python :: 3.4
Classifier: Programming Language :: Python :: 3.5
Classifier: Programming Language :: Python :: 3.6
Requires-Dist: boto3 (==1.4.4)
Requires-Dist: botocore (<2.0.0,>=1.5.62)
Requires-Dist: click (==6.6)
Requires-Dist: docutils (<0.15,>=0.12)
Requires-Dist: jmespath (<0.10.0,>=0.9.0)
Requires-Dist: pyaml (==15.8.2)
Requires-Dist: python-dateutil (<2.8.0,>=2.5.3)
Requires-Dist: PyYAML (<3.14,>=3.11)
Requires-Dist: six (<1.12.0,>=1.10.0)
Requires-Dist: futures; python_version <= "3.0"
